tifuun_sensitivity/__init__.py
tifuun_sensitivity/atmosphere.py
tifuun_sensitivity/cascade.py
tifuun_sensitivity/data/DESHIMA2.py
tifuun_sensitivity/data/QOfilterstack.npy
tifuun_sensitivity/data/atm.csv
tifuun_sensitivity/filterbank.py
tifuun_sensitivity/instruments.py
tifuun_sensitivity/physics.py
tifuun_sensitivity/simulator.py
tifuun_sensitivity-0.1.8.dist-info/METADATA
tifuun_sensitivity-0.1.8.dist-info/WHEEL
tifuun_sensitivity-0.1.8.dist-info/licenses/LICENSE
tifuun_sensitivity-0.1.8.dist-info/RECORD
