Metadata-Version: 2.4
Name: tifuun-sensitivity
Version: 0.1.8
Summary: Sensitivity calculator for TIFUUN
License: MIT
License-File: LICENSE
Author: Arend Moerman
Author-email: a.moerman-1@tudelft.nl
Requires-Python: >=3.10,<3.14
Classifier: License :: OSI Approved :: MIT License
Classifier: Programming Language :: Python :: 3
Classifier: Programming Language :: Python :: 3.10
Classifier: Programming Language :: Python :: 3.11
Classifier: Programming Language :: Python :: 3.12
Classifier: Programming Language :: Python :: 3.13
Requires-Dist: jupyter-io (>=1.0)
Requires-Dist: matplotlib (>=3.8)
Requires-Dist: numpy (>=1.26)
Requires-Dist: pandas (>=2.2)
Requires-Dist: scipy (>=1.13)
